sqlalchemy_nest/__init__.py
sqlalchemy_nest/orm.py
sqlalchemy_nest-1.2.2.dist-info/LICENSE
sqlalchemy_nest-1.2.2.dist-info/METADATA
sqlalchemy_nest-1.2.2.dist-info/WHEEL
sqlalchemy_nest-1.2.2.dist-info/RECORD
