Metadata-Version: 2.1
Name: sqlalchemy-nest
Version: 1.2.2
Summary: easy create nested models for sqlalchemy
Home-page: https://github.com/satorudev976/sqlalchemy-nest.git
License: MIT
Keywords: sqlalchemy,nest,sqlalchemy-nest
Author: satoru
Requires-Python: >=3.9,<4.0
Classifier: Development Status :: 5 - Production/Stable
Classifier: Intended Audience :: Developers
Classifier: License :: OSI Approved :: MIT License
Classifier: Programming Language :: Python
Classifier: Programming Language :: Python :: 3
Classifier: Programming Language :: Python :: 3.9
Classifier: Programming Language :: Python :: 3.10
Classifier: Programming Language :: Python :: 3.11
Classifier: Programming Language :: Python :: 3.12
Classifier: Topic :: Software Development :: Libraries :: Python Modules
Requires-Dist: SQLAlchemy (>=0.7)
Project-URL: Repository, https://github.com/satorudev976/sqlalchemy-nest.git
